odoo/addons/base_copy_user_access/README.rst
odoo/addons/base_copy_user_access/__init__.py
odoo/addons/base_copy_user_access/__manifest__.py
odoo/addons/base_copy_user_access/i18n/base_copy_user_access.pot
odoo/addons/base_copy_user_access/i18n/id.po
odoo/addons/base_copy_user_access/security/ir.model.access.csv
odoo/addons/base_copy_user_access/static/description/icon.png
odoo/addons/base_copy_user_access/tests/__init__.py
odoo/addons/base_copy_user_access/tests/test_copy_user_access.py
odoo/addons/base_copy_user_access/wizards/__init__.py
odoo/addons/base_copy_user_access/wizards/base_copy_user_access.py
odoo/addons/base_copy_user_access/wizards/base_copy_user_access.xml
odoo14_addon_base_copy_user_access-14.0.1.0.1.dist-info/METADATA
odoo14_addon_base_copy_user_access-14.0.1.0.1.dist-info/WHEEL
odoo14_addon_base_copy_user_access-14.0.1.0.1.dist-info/top_level.txt
odoo14_addon_base_copy_user_access-14.0.1.0.1.dist-info/RECORD
